{
    "_custom_": true, 
    "_ref_": 134261404, 
    "attach_models": [
        {
            "cast_shadow": true, 
            "material_alpha": 1, 
            "material_change": 0, 
            "material_color": [
                255, 
                255, 
                255
            ], 
            "material_color_intensity": 1, 
            "model": 202243, 
            "offset": {
                "__tuple__": true, 
                "items": [
                    -0.3688468933105469, 
                    0.0, 
                    0.015878677368164062
                ]
            }, 
            "receive_decal": false, 
            "rotate": {
                "__tuple__": true, 
                "items": [
                    8.847355753762208e-15, 
                    89.99999999999999, 
                    0.0000020137847266056124
                ]
            }, 
            "scale": {
                "__tuple__": true, 
                "items": [
                    1.0000000000000007, 
                    1.0000000000000007, 
                    1.0
                ]
            }, 
            "use_physics": false
        }, 
        {
            "cast_shadow": true, 
            "material_alpha": 1, 
            "material_change": 0, 
            "material_color": [
                255, 
                255, 
                255
            ], 
            "material_color_intensity": 1, 
            "model": 202243, 
            "offset": {
                "__tuple__": true, 
                "items": [
                    0.018848419189453125, 
                    0.0, 
                    -0.421356201171875
                ]
            }, 
            "receive_decal": false, 
            "rotate": {
                "__tuple__": true, 
                "items": [
                    0.0, 
                    0.0, 
                    0.0
                ]
            }, 
            "scale": {
                "__tuple__": true, 
                "items": [
                    1.0, 
                    1.0, 
                    1.0
                ]
            }, 
            "use_physics": false
        }, 
        {
            "cast_shadow": true, 
            "material_alpha": 1, 
            "material_change": 0, 
            "material_color": [
                255, 
                255, 
                255
            ], 
            "material_color_intensity": 1, 
            "model": 202236, 
            "offset": {
                "__tuple__": true, 
                "items": [
                    -0.003917694091796875, 
                    0.0, 
                    0.0104217529296875
                ]
            }, 
            "receive_decal": false, 
            "rotate": {
                "__tuple__": true, 
                "items": [
                    0.0, 
                    0.0, 
                    0.0
                ]
            }, 
            "scale": {
                "__tuple__": true, 
                "items": [
                    1.0, 
                    1.0, 
                    1.0
                ]
            }, 
            "use_physics": false
        }, 
        {
            "cast_shadow": true, 
            "material_alpha": 1, 
            "material_change": 0, 
            "material_color": [
                255, 
                255, 
                255
            ], 
            "material_color_intensity": 1, 
            "model": 202243, 
            "offset": {
                "__tuple__": true, 
                "items": [
                    -0.016201019287109375, 
                    0.0, 
                    0.36000633239746094
                ]
            }, 
            "receive_decal": false, 
            "rotate": {
                "__tuple__": true, 
                "items": [
                    0.0, 
                    0.0, 
                    0.0
                ]
            }, 
            "scale": {
                "__tuple__": true, 
                "items": [
                    1.0, 
                    1.0, 
                    1.0
                ]
            }, 
            "use_physics": false
        }, 
        {
            "cast_shadow": true, 
            "material_alpha": 1, 
            "material_change": 0, 
            "material_color": [
                255, 
                255, 
                255
            ], 
            "material_color_intensity": 1, 
            "model": 202243, 
            "offset": {
                "__tuple__": true, 
                "items": [
                    0.3632469177246094, 
                    0.0, 
                    0.018884658813476562
                ]
            }, 
            "receive_decal": false, 
            "rotate": {
                "__tuple__": true, 
                "items": [
                    8.847355753762208e-15, 
                    89.99999999999999, 
                    0.0000020137847266056124
                ]
            }, 
            "scale": {
                "__tuple__": true, 
                "items": [
                    1.0000000000000007, 
                    1.0000000000000007, 
                    1.0
                ]
            }, 
            "use_physics": false
        }, 
        {
            "cast_shadow": true, 
            "material_alpha": 1, 
            "material_change": 0, 
            "material_color": [
                255, 
                255, 
                255
            ], 
            "material_color_intensity": 1, 
            "model": 202237, 
            "offset": {
                "__tuple__": true, 
                "items": [
                    0.006870269775390625, 
                    6.150000095367432, 
                    0.016164779663085938
                ]
            }, 
            "receive_decal": false, 
            "rotate": {
                "__tuple__": true, 
                "items": [
                    2.4774725817219763e-22, 
                    0.0000020137847354529694, 
                    -179.99999899310762
                ]
            }, 
            "scale": {
                "__tuple__": true, 
                "items": [
                    1.7999999523162855, 
                    1.7999999523162844, 
                    1.7999999523162853
                ]
            }, 
            "use_physics": false
        }
    ], 
    "cast_shadow": true, 
    "collision_box": {
        "__tuple__": true, 
        "items": [
            [
                -5, 
                5
            ], 
            [
                -5, 
                -5
            ], 
            [
                5, 
                -5
            ], 
            [
                5, 
                5
            ]
        ]
    }, 
    "collision_height": {
        "__tuple__": true, 
        "items": []
    }, 
    "collision_points": {
        "__tuple__": true, 
        "items": [
            [
                -2, 
                -2
            ], 
            [
                1, 
                1
            ], 
            0
        ]
    }, 
    "description": 365580743, 
    "effect_list": [], 
    "icon": 100000, 
    "key": 134261404, 
    "kv": {}, 
    "material_alpha": 0, 
    "material_change": 0, 
    "material_color": {
        "__tuple__": true, 
        "items": [
            255, 
            255, 
            255
        ]
    }, 
    "material_color_intensity": 0, 
    "model": 103014, 
    "name": -956338120, 
    "receive_decal": false, 
    "scale": 1.0, 
    "suffix": "", 
    "tags": {
        "__tuple__": true, 
        "items": []
    }, 
    "uid": "134261404", 
    "use_physics": false
}